lantern/__init__.py
lantern/client.py
lantern/setup.py
lantern/utils.py
lantern_client-0.0.6.dist-info/LICENSE
lantern_client-0.0.6.dist-info/METADATA
lantern_client-0.0.6.dist-info/WHEEL
lantern_client-0.0.6.dist-info/top_level.txt
lantern_client-0.0.6.dist-info/RECORD
