Metadata-Version: 2.1
Name: lantern-client
Version: 0.0.6
Summary: Python client for Lantern
Home-page: https://github.com/lanterndata/lantern-python
Author: Varik Matevosyan
Author-email: varik@lantern.dev
License: MIT
Project-URL: Bug Tracker, https://github.com/lanterndata/lantern-python/issues
Classifier: Programming Language :: Python :: 3
Classifier: License :: OSI Approved :: MIT License
Classifier: Operating System :: OS Independent
Requires-Python: >=3.8
License-File: LICENSE
Requires-Dist: psycopg2-binary ==2.9.10
Requires-Dist: numpy
